langchain_zunno/__init__.py
langchain_zunno/embeddings.py
langchain_zunno/llm.py
langchain_zunno-0.1.6.dist-info/licenses/LICENSE
langchain_zunno-0.1.6.dist-info/METADATA
langchain_zunno-0.1.6.dist-info/WHEEL
langchain_zunno-0.1.6.dist-info/top_level.txt
langchain_zunno-0.1.6.dist-info/RECORD
