Metadata-Version: 2.4
Name: langchain-zunno
Version: 0.1.6
Summary: LangChain integration for Zunno LLM and Embeddings
Author-email: Amit Kumar <amit@zunno.ai>
Maintainer-email: Amit Kumar <amit@zunno.ai>
License: MIT
Project-URL: Homepage, https://github.com/zunno/langchain-zunno
Project-URL: Documentation, https://github.com/zunno/langchain-zunno#readme
Project-URL: Repository, https://github.com/zunno/langchain-zunno
Project-URL: Bug Tracker, https://github.com/zunno/langchain-zunno/issues
Keywords: langchain,llm,embeddings,zunno,ai,machine-learning
Classifier: Development Status :: 3 - Alpha
Classifier: Intended Audience :: Developers
Classifier: License :: OSI Approved :: MIT License
Classifier: Operating System :: OS Independent
Classifier: Programming Language :: Python :: 3
Classifier: Programming Language :: Python :: 3.8
Classifier: Programming Language :: Python :: 3.9
Classifier: Programming Language :: Python :: 3.10
Classifier: Programming Language :: Python :: 3.11
Classifier: Programming Language :: Python :: 3.12
Classifier: Topic :: Scientific/Engineering :: Artificial Intelligence
Classifier: Topic :: Software Development :: Libraries :: Python Modules
Requires-Python: >=3.8
License-File: LICENSE
Requires-Dist: langchain>=0.1.0
Requires-Dist: langchain-core>=0.1.0
Requires-Dist: requests>=2.25.0
Requires-Dist: httpx>=0.24.0
Requires-Dist: pydantic>=2.0.0
Provides-Extra: dev
Requires-Dist: pytest>=7.0.0; extra == "dev"
Requires-Dist: pytest-asyncio>=0.21.0; extra == "dev"
Requires-Dist: black>=22.0.0; extra == "dev"
Requires-Dist: isort>=5.0.0; extra == "dev"
Requires-Dist: flake8>=4.0.0; extra == "dev"
Dynamic: license-file
